{
  "data": {
    "Datasets": [
      {
        "name": "ANAGRAFICA",
        "resource": {
          "id": "ANAGRAFICA",
          "name": "ANAGRAFICA"
        },
        "sinceVersion": "1.0"
      },
      {
        "mappedTo": [
          {
            "source": {
              "name": "AP"
            },
            "target": {
              "name": "OOM"
            }
          },
          {
            "source": {
              "name": "AP"
            },
            "target": {
              "name": "OOM"
            }
          }
        ],
        "name": "AP",
        "resource": {
          "id": "AP",
          "name": "AP"
        },
        "sinceVersion": "1.0"
      },
      {
        "mappedTo": [
          {
            "source": {
              "name": "ARS_ANAG_MED_RES_storico"
            },
            "target": {
              "name": "OOM"
            }
          },
          {
            "source": {
              "name": "ARS_ANAG_MED_RES_storico"
            },
            "target": {
              "name": "OOM"
            }
          }
        ],
        "name": "ARS_ANAG_MED_RES_storico",
        "resource": {
          "id": "ARS_ANAG_MED_RES_storico",
          "name": "ARS_ANAG_MED_RES_storico"
        },
        "sinceVersion": "1.0"
      },
      {
        "label": "ATHLETE Harmonised dataset with standardized fetal growth data: ATHLETE_fetal_growth_standardized",
        "name": "ATHLETE_fetal_growth_standardized",
        "resource": {
          "id": "GenR",
          "name": "The Generation R Study"
        },
        "sinceVersion": "1.0.0"
      },
      {
        "name": "avo_toimenpide",
        "resource": {
          "id": "AVOHILMO",
          "name": "Register of Primary Health Care Visits (AVOHILMO)"
        },
        "sinceVersion": "1.0"
      },
      {
        "description": "Table containing data concerning respiratory health questionnaires for children up to 3 years old",
        "label": "Respiratory_child_data",
        "name": "base_respi_enfant_20210326",
        "numberOfRows": 484,
        "resource": {
          "id": "Sepages",
          "name": "Suivi de l'Exposition \u00e0 la Pollution Atmosph\u00e9rique et Effet sur la"
        },
        "sinceVersion": "1.0.0",
        "unitOfObservation": {
          "name": "person"
        }
      },
      {
        "description": "Table containing data concerning first year of life of the child",
        "label": "child_data",
        "name": "bdd_1a_v1_1",
        "numberOfRows": 484,
        "resource": {
          "id": "Sepages",
          "name": "Suivi de l'Exposition \u00e0 la Pollution Atmosph\u00e9rique et Effet sur la"
        },
        "sinceVersion": "1.0.0",
        "unitOfObservation": {
          "name": "person"
        }
      },
      {
        "description": "Table containing  data concerning  second year of life of the child",
        "label": "child_data",
        "name": "bdd_2a_v_1_0",
        "numberOfRows": 484,
        "resource": {
          "id": "Sepages",
          "name": "Suivi de l'Exposition \u00e0 la Pollution Atmosph\u00e9rique et Effet sur la"
        },
        "sinceVersion": "1.0.0",
        "unitOfObservation": {
          "name": "person"
        }
      },
      {
        "description": "database with measurement of cotinine from a maternal urine sample and in children's urine at 6 years",
        "label": "database with measurement of cotinine from a maternal urine sample and in children's urine at 6 years",
        "name": "BDD_cotinine",
        "resource": {
          "id": "PELAGIE",
          "name": "Perturbateurs Endocriniens: \u00c9tude Longitudinale sur les Anomalies de la Grossesse, l\u2019Infertilit"
        },
        "sinceVersion": "1.0.0",
        "unitOfObservation": {
          "name": "Patient"
        }
      },
      {
        "description": "database with measurement of creatinine from a maternal urine sample and in children's urine at 6 years",
        "label": "database with measurement of creatinine from a maternal urine sample and in children's urine at 6 years",
        "name": "BDD_creatinine",
        "resource": {
          "id": "PELAGIE",
          "name": "Perturbateurs Endocriniens: \u00c9tude Longitudinale sur les Anomalies de la Grossesse, l\u2019Infertilit"
        },
        "sinceVersion": "1.0.0",
        "unitOfObservation": {
          "name": "Patient"
        }
      },
      {
        "description": "database with measurement of OPs from a maternal urine sample and in children's urine at 6 years",
        "label": "database with measurement of OPs from a maternal urine sample and in children's urine at 6 years",
        "name": "BDD_ethers",
        "resource": {
          "id": "PELAGIE",
          "name": "Perturbateurs Endocriniens: \u00c9tude Longitudinale sur les Anomalies de la Grossesse, l\u2019Infertilit"
        },
        "sinceVersion": "1.0.0",
        "unitOfObservation": {
          "name": "Patient"
        }
      },
      {
        "description": "Table containing data concerning pregnancy",
        "label": "pregnancy_data",
        "name": "bdd_grossesse_v5_1",
        "numberOfRows": 484,
        "resource": {
          "id": "Sepages",
          "name": "Suivi de l'Exposition \u00e0 la Pollution Atmosph\u00e9rique et Effet sur la"
        },
        "sinceVersion": "1.0.0",
        "unitOfObservation": {
          "name": "person"
        }
      },
      {
        "description": "database with measurement of metals in a sample of mothers' hair during the third trimester",
        "label": "database with measurement of metals in a sample of mothers' hair during the third trimester",
        "name": "BDD_mercure",
        "resource": {
          "id": "PELAGIE",
          "name": "Perturbateurs Endocriniens: \u00c9tude Longitudinale sur les Anomalies de la Grossesse, l\u2019Infertilit"
        },
        "sinceVersion": "1.0.0",
        "unitOfObservation": {
          "name": "Patient"
        }
      },
      {
        "description": "database with measurement of OPs from a maternal urine sample and in children's urine at 6 years",
        "label": "database with measurement of OPs from a maternal urine sample and in children's urine at 6 years",
        "name": "BDD_OP",
        "resource": {
          "id": "PELAGIE",
          "name": "Perturbateurs Endocriniens: \u00c9tude Longitudinale sur les Anomalies de la Grossesse, l\u2019Infertilit"
        },
        "sinceVersion": "1.0.0",
        "unitOfObservation": {
          "name": "Patient"
        }
      },
      {
        "description": "Table containing data concerning father of the child SEPAGES",
        "label": "father_data",
        "name": "bdd_pere_1_2",
        "numberOfRows": 410,
        "resource": {
          "id": "Sepages",
          "name": "Suivi de l'Exposition \u00e0 la Pollution Atmosph\u00e9rique et Effet sur la"
        },
        "sinceVersion": "1.0.0",
        "unitOfObservation": {
          "name": "person"
        }
      },
      {
        "description": "database with PFASs measurement from cord blood and in the blood of children at 12 years",
        "label": "database with PFASs measurement from cord blood and in the blood of children at 12 years",
        "name": "BDD_perfluores",
        "resource": {
          "id": "PELAGIE",
          "name": "Perturbateurs Endocriniens: \u00c9tude Longitudinale sur les Anomalies de la Grossesse, l\u2019Infertilit"
        },
        "sinceVersion": "1.0.0",
        "unitOfObservation": {
          "name": "Patient"
        }
      },
      {
        "description": "database with phtalates and phenols measurement from maternal urine sample",
        "label": "database with phtalates and phenols measurement from maternal urine sample",
        "name": "BDD_phtalates_phenols",
        "resource": {
          "id": "PELAGIE",
          "name": "Perturbateurs Endocriniens: \u00c9tude Longitudinale sur les Anomalies de la Grossesse, l\u2019Infertilit"
        },
        "sinceVersion": "1.0.0",
        "unitOfObservation": {
          "name": "Patient"
        }
      },
      {
        "description": "database with POPs measurement from cord blood and in the blood of children at 12 years",
        "label": "database with POPs measurement from cord blood and in the blood of children at 12 years",
        "name": "BDD_pop",
        "resource": {
          "id": "PELAGIE",
          "name": "Perturbateurs Endocriniens: \u00c9tude Longitudinale sur les Anomalies de la Grossesse, l\u2019Infertilit"
        },
        "sinceVersion": "1.0.0",
        "unitOfObservation": {
          "name": "Patient"
        }
      },
      {
        "description": "blood pressure of the child measured during G21 cohort follow-ups",
        "label": "blood pressure",
        "name": "blood_pressure",
        "resource": {
          "id": "G21",
          "name": "Generation 21"
        },
        "sinceVersion": "1.0.0"
      },
      {
        "name": "bloodpressure after birth",
        "resource": {
          "id": "ENVIRONAGE",
          "name": "ENVIRonmental influence ON early AGEing"
        }
      },
      {
        "name": "cdm_1",
        "resource": {
          "id": "testNetwork1",
          "name": "name for test network1"
        }
      },
      {
        "name": "CDM_SOURCE",
        "resource": {
          "id": "OOM",
          "name": "OOM"
        },
        "sinceVersion": "2.2"
      },
      {
        "description": "Table containing data concerning breastfeeding",
        "label": "breastfeeding_data",
        "name": "ch_bf_mr&ag_2021-12-02_5",
        "numberOfRows": 484,
        "resource": {
          "id": "Sepages",
          "name": "Suivi de l'Exposition \u00e0 la Pollution Atmosph\u00e9rique et Effet sur la"
        },
        "sinceVersion": "1.0.0",
        "unitOfObservation": {
          "name": "person"
        }
      },
      {
        "label": "Chemicals (ATHLETE)",
        "name": "chemicals_ath",
        "resource": {
          "id": "ATHLETE",
          "name": "Advancing Tools for Human Early Lifecourse Exposome Research and Translation"
        },
        "sinceVersion": "1.1.0"
      },
      {
        "label": "child",
        "name": "child",
        "resource": {
          "id": "G21",
          "name": "Generation 21"
        },
        "sinceVersion": "1",
        "unitOfObservation": {
          "name": "person"
        }
      },
      {
        "label": "DataWiki dataset CHILD-ALLGENERALDATA_12112020",
        "name": "CHILD-ALLGENERALDATA_12112020",
        "resource": {
          "id": "GenR",
          "name": "The Generation R Study"
        },
        "sinceVersion": "1.0.0"
      },
      {
        "mappedTo": [
          {
            "source": {
              "name": "COD_FARMACI_SPF"
            },
            "target": {
              "name": "OOM"
            }
          }
        ],
        "name": "COD_FARMACI_SPF",
        "resource": {
          "id": "COD_FARMACI_SPF",
          "name": "COD_FARMACI_SPF"
        },
        "sinceVersion": "1.0"
      },
      {
        "description": "Table containing Ids",
        "label": "Id_data",
        "name": "code_helix_athlete",
        "numberOfRows": 484,
        "resource": {
          "id": "Sepages",
          "name": "Suivi de l'Exposition \u00e0 la Pollution Atmosph\u00e9rique et Effet sur la"
        },
        "sinceVersion": "1.0.0",
        "unitOfObservation": {
          "name": "person"
        }
      },
      {
        "name": "core",
        "resource": {
          "id": "NFBC1966",
          "name": "NFBC1966"
        },
        "sinceVersion": "1.0.0"
      },
      {
        "name": "core",
        "resource": {
          "id": "GenR",
          "name": "The Generation R Study"
        },
        "sinceVersion": "1.0.0"
      },
      {
        "name": "core",
        "resource": {
          "id": "LifeCycle",
          "name": "The LifeCycle Project"
        },
        "sinceVersion": "1.0.0",
        "unitOfObservation": {
          "name": "Patient"
        }
      },
      {
        "mappedTo": [
          {
            "source": {
              "name": "Dutch institute for health and welfare"
            },
            "target": {
              "name": "OOM"
            }
          }
        ],
        "name": "CPA1",
        "resource": {
          "id": "DHL",
          "name": "Dutch institute for health and welfare"
        },
        "sinceVersion": "1.0"
      },
      {
        "mappedTo": [
          {
            "source": {
              "name": "Dutch institute for health and welfare"
            },
            "target": {
              "name": "OOM"
            }
          }
        ],
        "name": "CPA2",
        "resource": {
          "id": "DHL",
          "name": "Dutch institute for health and welfare"
        },
        "sinceVersion": "1.0"
      },
      {
        "description": "Father date of birth from 6 and 12 years old follow-ups",
        "label": "Father date of birth",
        "name": "datenaisspere",
        "resource": {
          "id": "PELAGIE",
          "name": "Perturbateurs Endocriniens: \u00c9tude Longitudinale sur les Anomalies de la Grossesse, l\u2019Infertilit"
        },
        "sinceVersion": "1.0.0",
        "unitOfObservation": {
          "name": "Patient"
        }
      },
      {
        "description": "Table containing date of birth of the father",
        "label": "ddn_father",
        "name": "ddn_pere",
        "numberOfRows": 484,
        "resource": {
          "id": "Sepages",
          "name": "Suivi de l'Exposition \u00e0 la Pollution Atmosph\u00e9rique et Effet sur la"
        },
        "sinceVersion": "1.0.0",
        "unitOfObservation": {
          "name": "person"
        }
      },
      {
        "name": "DIAGNOSTIC",
        "resource": {
          "id": "DIAGNOSTIC",
          "name": "DIAGNOSTIC"
        },
        "sinceVersion": "1.0"
      },
      {
        "name": "EFEMERIS_PRESCRIPTION",
        "resource": {
          "id": "EFEMERIS_PRESCRIPTION",
          "name": "EFEMERIS_PRESCRIPTION"
        },
        "sinceVersion": "1.0"
      },
      {
        "description": "Table containing data concerning mother's respiratory examination",
        "label": "Respiratory_function_test_mother",
        "name": "efr_mere_LMAB_20210902_26",
        "numberOfRows": 484,
        "resource": {
          "id": "Sepages",
          "name": "Suivi de l'Exposition \u00e0 la Pollution Atmosph\u00e9rique et Effet sur la"
        },
        "sinceVersion": "1.0.0",
        "unitOfObservation": {
          "name": "person"
        }
      },
      {
        "description": "Table containing data concerning  father's respiratory examination",
        "label": "Respiratory_function_test_father",
        "name": "efr_pere_LMAB_20210902_26",
        "numberOfRows": 484,
        "resource": {
          "id": "Sepages",
          "name": "Suivi de l'Exposition \u00e0 la Pollution Atmosph\u00e9rique et Effet sur la"
        },
        "sinceVersion": "1.0.0",
        "unitOfObservation": {
          "name": "person"
        }
      },
      {
        "name": "EUROCAT",
        "resource": {
          "id": "OOM",
          "name": "OOM"
        },
        "sinceVersion": "2.2"
      },
      {
        "mappedFrom": [
          {
            "source": {
              "name": "Dutch institute for health and welfare"
            },
            "target": {
              "name": "OOM"
            }
          },
          {
            "source": {
              "name": "Dutch institute for health and welfare"
            },
            "target": {
              "name": "OOM"
            }
          },
          {
            "source": {
              "name": "ARS_PS"
            },
            "target": {
              "name": "OOM"
            }
          },
          {
            "source": {
              "name": "SALM"
            },
            "target": {
              "name": "OOM"
            }
          },
          {
            "source": {
              "name": "SEA"
            },
            "target": {
              "name": "OOM"
            }
          }
        ],
        "name": "EVENTS",
        "resource": {
          "id": "OOM",
          "name": "OOM"
        },
        "sinceVersion": "2.2"
      },
      {
        "name": "EXE",
        "resource": {
          "id": "EXE",
          "name": "EXE"
        },
        "sinceVersion": "1.0"
      },
      {
        "name": "FARMACEUTICA",
        "resource": {
          "id": "FARMACEUTICA",
          "name": "FARMACEUTICA"
        },
        "sinceVersion": "1.0"
      },
      {
        "label": "DataWiki dataset FETALCRL_22112016",
        "name": "FETALCRL_22112016",
        "resource": {
          "id": "GenR",
          "name": "The Generation R Study"
        },
        "sinceVersion": "1.0.0"
      },
      {
        "label": "DataWiki dataset FETALGROWTH_22112016",
        "name": "FETALGROWTH_22112016",
        "resource": {
          "id": "GenR",
          "name": "The Generation R Study"
        },
        "sinceVersion": "1.0.0"
      },
      {
        "label": "DataWiki dataset FETALPLACENTA_22112016",
        "name": "FETALPLACENTA_22112016",
        "resource": {
          "id": "GenR",
          "name": "The Generation R Study"
        },
        "sinceVersion": "1.0.0"
      },
      {
        "description": "database with geocodes of the participants",
        "label": "database with geocodes of the participants",
        "name": "geocodes",
        "resource": {
          "id": "PELAGIE",
          "name": "Perturbateurs Endocriniens: \u00c9tude Longitudinale sur les Anomalies de la Grossesse, l\u2019Infertilit"
        },
        "unitOfObservation": {
          "name": "Patient"
        }
      },
      {
        "description": "Non existing variables created for ATHLETE",
        "label": "Variables harmonized for ATHLETE or LifeCycle",
        "name": "harmonized",
        "resource": {
          "id": "PELAGIE",
          "name": "Perturbateurs Endocriniens: \u00c9tude Longitudinale sur les Anomalies de la Grossesse, l\u2019Infertilit"
        },
        "sinceVersion": "1.0.0",
        "unitOfObservation": {
          "name": "Patient"
        }
      },
      {
        "name": "INSTANCE",
        "resource": {
          "id": "OOM",
          "name": "OOM"
        },
        "sinceVersion": "2.2"
      },
      {
        "name": "kayntisyy_icd10",
        "resource": {
          "id": "AVOHILMO",
          "name": "Register of Primary Health Care Visits (AVOHILMO)"
        },
        "sinceVersion": "1.0"
      },
      {
        "name": "kayntisyy_icpc2",
        "resource": {
          "id": "AVOHILMO",
          "name": "Register of Primary Health Care Visits (AVOHILMO)"
        },
        "sinceVersion": "1.0"
      },
      {
        "description": "Date of birth updated in 2021",
        "label": "Update of the date of birth",
        "name": "maj_ddn_2021",
        "resource": {
          "id": "PELAGIE",
          "name": "Perturbateurs Endocriniens: \u00c9tude Longitudinale sur les Anomalies de la Grossesse, l\u2019Infertilit"
        },
        "sinceVersion": "1.0.0",
        "unitOfObservation": {
          "name": "Patient"
        }
      },
      {
        "name": "MBRN",
        "resource": {
          "id": "MBRN",
          "name": "MBRN"
        },
        "sinceVersion": "1.0"
      },
      {
        "name": "MBRN_child",
        "resource": {
          "id": "MBRN",
          "name": "MBRN"
        },
        "sinceVersion": "1.0"
      },
      {
        "name": "MBRN_mother",
        "resource": {
          "id": "MBRN",
          "name": "MBRN"
        },
        "sinceVersion": "1.0"
      },
      {
        "name": "measurements after birth",
        "resource": {
          "id": "ENVIRONAGE",
          "name": "ENVIRonmental influence ON early AGEing"
        }
      },
      {
        "name": "measurements at FU1",
        "resource": {
          "id": "ENVIRONAGE",
          "name": "ENVIRonmental influence ON early AGEing"
        }
      },
      {
        "mappedFrom": [
          {
            "source": {
              "name": "AP"
            },
            "target": {
              "name": "OOM"
            }
          }
        ],
        "name": "MEDICAL_OBSERVATIONS",
        "resource": {
          "id": "OOM",
          "name": "OOM"
        },
        "sinceVersion": "2.2"
      },
      {
        "mappedFrom": [
          {
            "source": {
              "name": "SPF"
            },
            "target": {
              "name": "OOM"
            }
          }
        ],
        "name": "MEDICINES",
        "resource": {
          "id": "OOM",
          "name": "OOM"
        },
        "sinceVersion": "2.2"
      },
      {
        "name": "METADATA",
        "resource": {
          "id": "OOM",
          "name": "OOM"
        },
        "sinceVersion": "2.2"
      },
      {
        "description": "description for test dataset 2 for test cohort 1",
        "keywords": [
          {
            "name": "Supplements (M)"
          },
          {
            "name": "School age"
          },
          {
            "name": "Preschool age - Dietary behavior"
          },
          {
            "name": "School age - Method of dietary assessment"
          },
          {
            "name": "School age - Exact age at dietary assessment"
          },
          {
            "name": "School age - Supplements"
          },
          {
            "name": "School age - Food groups"
          },
          {
            "name": "School age - Nutrients"
          },
          {
            "code": "Tech_devices",
            "name": "Technological devices"
          },
          {
            "name": "DASH diet index"
          },
          {
            "name": "Method of dietary assessment (M)"
          },
          {
            "name": "Method of dietary assessment (F)"
          },
          {
            "name": "Gestational week at dietary assessment"
          },
          {
            "name": "Food groups (M)"
          },
          {
            "code": "Leisure_act",
            "name": "Leisure activities"
          },
          {
            "name": "School age - Dietary behavior"
          },
          {
            "name": "Food groups (F)"
          },
          {
            "name": "Nutrients (M)"
          },
          {
            "name": "Nutrients (F)"
          },
          {
            "name": "Supplements (F)"
          },
          {
            "code": "Other_lifestyle",
            "name": "Other and unspecified lifestyle information"
          },
          {
            "name": "School age - DASH diet index"
          },
          {
            "name": "DASH diet index (M)"
          },
          {
            "name": "DASH diet index (F)"
          },
          {
            "code": "Phys_act",
            "name": "Physical activity"
          },
          {
            "code": "Transportation",
            "name": "Transportation"
          },
          {
            "code": "Pers_hygiene",
            "name": "Personal hygiene"
          },
          {
            "code": "Sleep",
            "name": "Sleep"
          },
          {
            "code": "Misbehav_crim",
            "name": "Misbehaviour and criminality"
          },
          {
            "name": "Preschool age - Method of dietary assessment"
          },
          {
            "name": "Preschool age - Food groups"
          },
          {
            "name": "Preschool age - Supplements"
          },
          {
            "name": "Preschool age - Nutrients"
          },
          {
            "code": "Lifestyle_behaviours",
            "name": "Lifestyle and behaviours"
          },
          {
            "code": "Tobacco",
            "name": "Tobacco"
          },
          {
            "name": "Maternal smoking"
          },
          {
            "name": "Paternal smoking"
          },
          {
            "code": "Alcohol",
            "name": "Alcohol"
          },
          {
            "code": "Drugs",
            "name": "Drugs"
          },
          {
            "code": "Nutrition",
            "name": "Nutrition"
          },
          {
            "name": "Preschool age"
          },
          {
            "name": "Method of dietary assessment (Preschool)"
          },
          {
            "name": "Exact age at dietary assessment (Preschool)"
          },
          {
            "name": "Food groups (Preschool)"
          },
          {
            "name": "Supplements (Preschool)"
          },
          {
            "name": "Nutrients (Preschool)"
          },
          {
            "name": "Dietary behavior (Preschool)"
          },
          {
            "name": "Method of dietary assessment (School)"
          },
          {
            "name": "Exact age at dietary assessment (School)"
          },
          {
            "name": "Supplements (School)"
          },
          {
            "code": "Sex_behav",
            "name": "Sexual behaviours and orientation"
          },
          {
            "name": "Food groups (School)"
          },
          {
            "name": "Nutrients (School)"
          },
          {
            "name": "Dietary behavior (School)"
          }
        ],
        "label": "label for test dataset 2 for test cohort 1",
        "name": "name of test dataset 2 for test cohort 1",
        "numberOfRows": 64000,
        "resource": {
          "id": "testCohort1",
          "name": "Name for test cohort 1"
        },
        "sinceVersion": "1980",
        "unitOfObservation": {
          "name": "observation"
        }
      },
      {
        "description": "Non existing variables created for ATHLETE",
        "label": "Created variables for ATHLETE",
        "name": "new",
        "resource": {
          "id": "PELAGIE",
          "name": "Perturbateurs Endocriniens: \u00c9tude Longitudinale sur les Anomalies de la Grossesse, l\u2019Infertilit"
        },
        "sinceVersion": "1.0.0",
        "unitOfObservation": {
          "name": "Patient"
        }
      },
      {
        "mappedFrom": [
          {
            "source": {
              "name": "ARS_ANAG_MED_RES_storico"
            },
            "target": {
              "name": "OOM"
            }
          }
        ],
        "name": "OBSERVATION_PERIODS",
        "resource": {
          "id": "OOM",
          "name": "OOM"
        },
        "sinceVersion": "2.2"
      },
      {
        "name": "outcome",
        "resource": {
          "id": "LifeCycle",
          "name": "The LifeCycle Project"
        },
        "sinceVersion": "1.0.0"
      },
      {
        "label": "Outcome (ATHLETE)",
        "name": "outcome_ath",
        "resource": {
          "id": "ATHLETE",
          "name": "Advancing Tools for Human Early Lifecourse Exposome Research and Translation"
        },
        "sinceVersion": "1.1.0"
      },
      {
        "name": "outcomes",
        "resource": {
          "id": "LifeCycle",
          "name": "The LifeCycle Project"
        },
        "sinceVersion": "1.0.0"
      },
      {
        "name": "palvelutapahtuma",
        "resource": {
          "id": "AVOHILMO",
          "name": "Register of Primary Health Care Visits (AVOHILMO)"
        },
        "sinceVersion": "1.0"
      },
      {
        "description": "Table containing data concerning assessment of phenols and phtalates during pregnancy",
        "label": "phenols_phthalates_pregnancy_data",
        "name": "PE_preg_mr_2021-12-02_379",
        "numberOfRows": 479,
        "resource": {
          "id": "Sepages",
          "name": "Suivi de l'Exposition \u00e0 la Pollution Atmosph\u00e9rique et Effet sur la"
        },
        "sinceVersion": "1.0.0",
        "unitOfObservation": {
          "name": "person"
        }
      },
      {
        "description": "database with blood concentrations of effect biomarkers at 12 years old",
        "label": "database with blood concentrations of effect biomarkers at 12 years old",
        "name": "pelagie_dosage12",
        "resource": {
          "id": "PELAGIE",
          "name": "Perturbateurs Endocriniens: \u00c9tude Longitudinale sur les Anomalies de la Grossesse, l\u2019Infertilit"
        },
        "unitOfObservation": {
          "name": "Patient"
        }
      },
      {
        "description": "Clinical examination at 12 years old",
        "label": "Clinical examination at 12 years old",
        "name": "pelagie_exam12",
        "resource": {
          "id": "PELAGIE",
          "name": "Perturbateurs Endocriniens: \u00c9tude Longitudinale sur les Anomalies de la Grossesse, l\u2019Infertilit"
        },
        "sinceVersion": "1.0.0",
        "unitOfObservation": {
          "name": "Patient"
        }
      },
      {
        "description": "Questionnaire at 11 years old of the child (Grandir et Changer)",
        "label": "Questionnaire at 11 years old of the child",
        "name": "pelagie_GC_q11",
        "resource": {
          "id": "PELAGIE",
          "name": "Perturbateurs Endocriniens: \u00c9tude Longitudinale sur les Anomalies de la Grossesse, l\u2019Infertilit"
        },
        "sinceVersion": "1.0.0",
        "unitOfObservation": {
          "name": "Patient"
        }
      },
      {
        "description": "This table contains the variables collected at baseline for PELAGIE (pregnancy and birth)",
        "label": "Baseline questionnaire in early pregnancy and data at birth",
        "name": "pelagie_q0",
        "resource": {
          "id": "PELAGIE",
          "name": "Perturbateurs Endocriniens: \u00c9tude Longitudinale sur les Anomalies de la Grossesse, l\u2019Infertilit"
        },
        "sinceVersion": "1.0.0",
        "unitOfObservation": {
          "name": "Patient"
        }
      },
      {
        "description": "Questionnaire at 2 years old of the child",
        "label": "Questionnaire at 2 years old of the child",
        "name": "pelagie_q2",
        "resource": {
          "id": "PELAGIE",
          "name": "Perturbateurs Endocriniens: \u00c9tude Longitudinale sur les Anomalies de la Grossesse, l\u2019Infertilit"
        },
        "sinceVersion": "1.0.0",
        "unitOfObservation": {
          "name": "Patient"
        }
      },
      {
        "description": "Questionnaire at 6 years old of the child",
        "label": "Questionnaire at 6 years old of the child",
        "name": "pelagie_q6",
        "resource": {
          "id": "PELAGIE",
          "name": "Perturbateurs Endocriniens: \u00c9tude Longitudinale sur les Anomalies de la Grossesse, l\u2019Infertilit"
        },
        "sinceVersion": "1.0.0",
        "unitOfObservation": {
          "name": "Patient"
        }
      },
      {
        "description": "Questionnaire at 12 years old of the child",
        "label": "Questionnaire at 12 years old of the child",
        "name": "pelagie_q12",
        "resource": {
          "id": "PELAGIE",
          "name": "Perturbateurs Endocriniens: \u00c9tude Longitudinale sur les Anomalies de la Grossesse, l\u2019Infertilit"
        },
        "sinceVersion": "1.0.0",
        "unitOfObservation": {
          "name": "Patient"
        }
      },
      {
        "description": "Neuropsychological tests at 6 years old",
        "label": "Neuropsychological tests at 6 years old",
        "name": "pepsy",
        "resource": {
          "id": "PELAGIE",
          "name": "Perturbateurs Endocriniens: \u00c9tude Longitudinale sur les Anomalies de la Grossesse, l\u2019Infertilit"
        },
        "sinceVersion": "1.0.0",
        "unitOfObservation": {
          "name": "Patient"
        }
      },
      {
        "name": "PERSON_RELATIONSHIPS",
        "resource": {
          "id": "OOM",
          "name": "OOM"
        },
        "sinceVersion": "2.2"
      },
      {
        "mappedFrom": [
          {
            "source": {
              "name": "ARS_ANAG_MED_RES_storico"
            },
            "target": {
              "name": "OOM"
            }
          }
        ],
        "name": "PERSONS",
        "resource": {
          "id": "OOM",
          "name": "OOM"
        },
        "sinceVersion": "2.2"
      },
      {
        "description": "Table containing data concerning assessment of pfas",
        "label": "pfas_data",
        "name": "PFAS_2021_12_10",
        "numberOfRows": 450,
        "resource": {
          "id": "Sepages",
          "name": "Suivi de l'Exposition \u00e0 la Pollution Atmosph\u00e9rique et Effet sur la"
        },
        "sinceVersion": "1.0.0",
        "unitOfObservation": {
          "name": "person"
        }
      },
      {
        "description": "Table containing data concerning assessment of phenols and phtalates during infancy",
        "label": "phenols_phthalates_infancy_data",
        "name": "phenols_phthalates_infancy_mr_585_2021-12-02",
        "numberOfRows": 443,
        "resource": {
          "id": "Sepages",
          "name": "Suivi de l'Exposition \u00e0 la Pollution Atmosph\u00e9rique et Effet sur la"
        },
        "sinceVersion": "1.0.0",
        "unitOfObservation": {
          "name": "person"
        }
      },
      {
        "name": "PHT",
        "resource": {
          "id": "PHT",
          "name": "PHT"
        },
        "sinceVersion": "1.0"
      },
      {
        "mappedFrom": [
          {
            "source": {
              "name": "SPA"
            },
            "target": {
              "name": "OOM"
            }
          }
        ],
        "name": "PROCEDURES",
        "resource": {
          "id": "OOM",
          "name": "OOM"
        },
        "sinceVersion": "2.2"
      },
      {
        "mappedFrom": [
          {
            "source": {
              "name": "COD_FARMACI_SPF"
            },
            "target": {
              "name": "OOM"
            }
          }
        ],
        "name": "PRODUCTS",
        "resource": {
          "id": "OOM",
          "name": "OOM"
        },
        "sinceVersion": "2.2"
      },
      {
        "mappedTo": [
          {
            "source": {
              "name": "ARS_PS"
            },
            "target": {
              "name": "OOM"
            }
          }
        ],
        "name": "PS",
        "resource": {
          "id": "ARS_PS",
          "name": "ARS_PS"
        },
        "sinceVersion": "1.0"
      },
      {
        "description": "Table containing data concerning mother's educational level",
        "label": "educational_level_mother_data",
        "name": "quest_mt1raa1",
        "numberOfRows": 484,
        "resource": {
          "id": "Sepages",
          "name": "Suivi de l'Exposition \u00e0 la Pollution Atmosph\u00e9rique et Effet sur la"
        },
        "sinceVersion": "1.0.0",
        "unitOfObservation": {
          "name": "person"
        }
      },
      {
        "mappedTo": [
          {
            "source": {
              "name": "RMR"
            },
            "target": {
              "name": "OOM"
            }
          },
          {
            "source": {
              "name": "RMR"
            },
            "target": {
              "name": "OOM"
            }
          }
        ],
        "name": "RMR",
        "resource": {
          "id": "RMR",
          "name": "RMR"
        },
        "sinceVersion": "1.0"
      },
      {
        "mappedTo": [
          {
            "source": {
              "name": "SALM"
            },
            "target": {
              "name": "OOM"
            }
          }
        ],
        "name": "SALM",
        "resource": {
          "id": "SALM",
          "name": "SALM"
        },
        "sinceVersion": "1.0"
      },
      {
        "mappedTo": [
          {
            "source": {
              "name": "SEA"
            },
            "target": {
              "name": "OOM"
            }
          }
        ],
        "name": "SEA",
        "resource": {
          "id": "SEA",
          "name": "SEA"
        },
        "sinceVersion": "1.0"
      },
      {
        "mappedTo": [
          {
            "source": {
              "name": "SPA"
            },
            "target": {
              "name": "OOM"
            }
          },
          {
            "source": {
              "name": "SPA"
            },
            "target": {
              "name": "OOM"
            }
          }
        ],
        "name": "SPA",
        "resource": {
          "id": "SPA",
          "name": "SPA"
        },
        "sinceVersion": "1.0"
      },
      {
        "name": "SPECIALISTICA",
        "resource": {
          "id": "SPECIALISTICA",
          "name": "SPECIALISTICA"
        },
        "sinceVersion": "1.0"
      },
      {
        "mappedTo": [
          {
            "source": {
              "name": "SPF"
            },
            "target": {
              "name": "OOM"
            }
          }
        ],
        "name": "SPF",
        "resource": {
          "id": "SPF",
          "name": "SPF"
        },
        "sinceVersion": "1.0"
      },
      {
        "mappedFrom": [
          {
            "source": {
              "name": "RMR"
            },
            "target": {
              "name": "OOM"
            }
          }
        ],
        "name": "SURVEY_ID",
        "resource": {
          "id": "OOM",
          "name": "OOM"
        },
        "sinceVersion": "2.2"
      },
      {
        "mappedFrom": [
          {
            "source": {
              "name": "RMR"
            },
            "target": {
              "name": "OOM"
            }
          }
        ],
        "name": "SURVEY_OBSERVATIONS",
        "resource": {
          "id": "OOM",
          "name": "OOM"
        },
        "sinceVersion": "2.2"
      },
      {
        "description": "Table containing data concerning child's Exposure to Tobacco Smoke",
        "label": "ETS_data",
        "name": "tabac_passif_enf",
        "numberOfRows": 484,
        "resource": {
          "id": "Sepages",
          "name": "Suivi de l'Exposition \u00e0 la Pollution Atmosph\u00e9rique et Effet sur la"
        },
        "sinceVersion": "1.0.0",
        "unitOfObservation": {
          "name": "person"
        }
      },
      {
        "description": "test description for dataset 1",
        "keywords": [
          {
            "code": "Social_environment",
            "name": "Social environment and relationships"
          },
          {
            "code": "Soc_network",
            "name": "Social network"
          },
          {
            "code": "Soc_participation",
            "name": "Social participation"
          },
          {
            "code": "Soc_support",
            "name": "Social support"
          },
          {
            "code": "Parenting",
            "name": "Parenting and familial environment"
          },
          {
            "code": "Other_soc_characteristics",
            "name": "Other social environment characteristics"
          },
          {
            "name": "Family mental health"
          }
        ],
        "label": "label for test dataset 1",
        "name": "test dataset for testCohort1",
        "numberOfRows": 30000,
        "resource": {
          "id": "testCohort1",
          "name": "Name for test cohort 1"
        },
        "sinceVersion": "1959",
        "unitOfObservation": {
          "name": "Patient"
        },
        "untilVersion": "1985"
      },
      {
        "description": "test description of dataset for cohort 2",
        "keywords": [
          {
            "name": "distance (traffic)"
          },
          {
            "name": "IgE (Food)"
          },
          {
            "name": "Any food allergic sensitization (IgE)"
          },
          {
            "name": "Skin prick test (Food)"
          },
          {
            "name": "Fish"
          },
          {
            "name": "Allergy"
          },
          {
            "name": "Fruit"
          },
          {
            "name": "Food allergy"
          },
          {
            "name": "Inhalant allergy"
          },
          {
            "name": "Any allergy"
          },
          {
            "name": "Allergic sensitization"
          },
          {
            "name": "Food"
          },
          {
            "name": "Food_IgE"
          },
          {
            "name": "IgE - Any food allergic sensitization"
          },
          {
            "name": "Food_Skin prick test"
          },
          {
            "name": "Skin prick test - Any food allergic sensitization"
          },
          {
            "name": "Chicken egg"
          },
          {
            "name": "Cow milk"
          },
          {
            "name": "Rye"
          },
          {
            "name": "Inhalant_Skin prick test"
          },
          {
            "name": "Nut"
          },
          {
            "name": "Peanut"
          },
          {
            "name": "Sesame"
          },
          {
            "name": "Shellfish"
          },
          {
            "name": "Wheat"
          },
          {
            "name": "Inhalant"
          },
          {
            "name": "Inhalant_IgE"
          },
          {
            "name": "IgE - Any inhalant allergic sensitization"
          },
          {
            "name": "IgE - Cat"
          },
          {
            "name": "IgE - House dust mite"
          },
          {
            "name": "Mould"
          },
          {
            "name": "Skin prick test - Any inhalant allergic sensitization"
          },
          {
            "name": "Skin prick test - Cat"
          },
          {
            "name": "Dog"
          },
          {
            "name": "Skin prick test - House dust mite"
          },
          {
            "name": "Grass"
          },
          {
            "name": "Tree"
          },
          {
            "name": "Urticaria"
          },
          {
            "name": "Anaphylaxis"
          },
          {
            "name": "Cat (Skin prick test)"
          },
          {
            "code": "Physical_environment",
            "name": "Physical environment"
          },
          {
            "name": "Pets"
          },
          {
            "name": "Cats (any)"
          },
          {
            "name": "main_land_use_continuous_urban_fabric"
          },
          {
            "name": "Cats (number)"
          },
          {
            "name": "Dogs (any)"
          },
          {
            "name": "Dogs (number)"
          },
          {
            "name": "Furry Pets"
          },
          {
            "code": "Housing",
            "name": "Housing characteristics"
          },
          {
            "code": "Neighborhood",
            "name": "Built environment/neighbourhood characteristics"
          },
          {
            "name": "Social context"
          },
          {
            "name": "area_level_ses_tertiles"
          },
          {
            "name": "area_level_ses_quintiles"
          },
          {
            "name": "population_density"
          },
          {
            "name": "building_density100"
          },
          {
            "name": "building_density300"
          },
          {
            "name": "connectivity_density100"
          },
          {
            "name": "connectivity_density300"
          },
          {
            "name": "access_to_public_transport_lines100"
          },
          {
            "name": "access_to_public_transport_lines300"
          },
          {
            "name": "main_land_use_industrial"
          },
          {
            "name": "Any food allergic sensitization (Skin prick test)"
          },
          {
            "name": "IgE (Inhalant)"
          },
          {
            "name": "main_land_use_forests"
          },
          {
            "name": "main_land_use_other"
          },
          {
            "name": "access_to_public_transport_lines500"
          },
          {
            "name": "access_to_public_transport_stops100"
          },
          {
            "name": "access_to_public_transport_stops300"
          },
          {
            "name": "access_to_public_transport_stops500"
          },
          {
            "name": "main_land_use_medium_urban_fabric"
          },
          {
            "name": "Any inhalant allergic sensitization (IgE)"
          },
          {
            "name": "Chemicals"
          },
          {
            "name": "Phenols"
          },
          {
            "name": "facilities_density"
          },
          {
            "name": "facilities_richness"
          },
          {
            "name": "land_use_mix"
          },
          {
            "name": "walkability"
          },
          {
            "name": "main_land_use_agricultural"
          },
          {
            "name": "main_land_use_airports"
          },
          {
            "name": "main_land_use_port"
          },
          {
            "name": "main_land_use_transports"
          },
          {
            "name": "main_land_use_green_urban"
          },
          {
            "name": "main_land_use_low_density"
          },
          {
            "name": "main_land_use_water"
          },
          {
            "code": "Workplace",
            "name": "Workplace characteristics"
          },
          {
            "code": "Radiation_exp",
            "name": "Radiation exposure"
          },
          {
            "code": "Chemical_exp",
            "name": "Chemical exposure"
          },
          {
            "name": "House dust mite (Skin prick test)"
          },
          {
            "name": "Phthalates"
          },
          {
            "name": "PFASs"
          },
          {
            "name": "Creatinine"
          },
          {
            "name": "OCs & PBDEs"
          },
          {
            "name": "Metals"
          },
          {
            "name": "OPs"
          },
          {
            "name": "Cotinine"
          },
          {
            "name": "PAHs"
          },
          {
            "name": "Glycolethers"
          },
          {
            "name": "Other pesticides"
          },
          {
            "name": "Passive smoking"
          },
          {
            "name": "Air pollution"
          },
          {
            "name": "no2"
          },
          {
            "name": "nox"
          },
          {
            "name": "pm25"
          },
          {
            "name": "pm25fe"
          },
          {
            "code": "Biological_exp",
            "name": "Biological exposure"
          },
          {
            "code": "Other_environment",
            "name": "Other physical environment characteristics"
          },
          {
            "name": "Meteorology"
          },
          {
            "name": "Cat (IgE)"
          },
          {
            "name": "pm25k"
          },
          {
            "name": "pm25cu"
          },
          {
            "name": "pm25ni"
          },
          {
            "name": "pm25s"
          },
          {
            "name": "Noise"
          },
          {
            "name": "House dust mite (IgE)"
          },
          {
            "name": "Skin prick test (Inhalant)"
          },
          {
            "name": "Any inhalant allergic sensitization  (Skin prick test)"
          },
          {
            "name": "pm25si"
          },
          {
            "name": "pm25v"
          },
          {
            "name": "pm25zn"
          },
          {
            "name": "pm25abs"
          },
          {
            "name": "pm10"
          },
          {
            "name": "pm10si"
          },
          {
            "name": "pm10v"
          },
          {
            "name": "pm10zn"
          },
          {
            "name": "pm10cu"
          },
          {
            "name": "pm10fe"
          },
          {
            "name": "pm10k"
          },
          {
            "name": "pm10ni"
          },
          {
            "name": "pm10s"
          },
          {
            "name": "pmcoarse"
          },
          {
            "name": "mean_temperature"
          },
          {
            "name": "minimum_temperature"
          },
          {
            "name": "maximum_temperature"
          },
          {
            "name": "mean_relative_humidity"
          },
          {
            "name": "minimum_relative_humidity"
          },
          {
            "name": "maximum_relative_humidity"
          },
          {
            "name": "DNA_damage_UV_dose"
          },
          {
            "name": "erythemal_UV_dose"
          },
          {
            "name": "vitamin_d_UV_dose"
          },
          {
            "name": "land_surface_temperature"
          },
          {
            "name": "meteo_distance"
          },
          {
            "name": "Natural spaces"
          },
          {
            "name": "blue_distance"
          },
          {
            "name": "green_distance"
          },
          {
            "name": "blue_size"
          },
          {
            "name": "green_size"
          },
          {
            "name": "blue_access"
          },
          {
            "name": "green_access"
          },
          {
            "name": "ndvi100"
          },
          {
            "name": "ndvi300"
          },
          {
            "name": "ndvi500"
          },
          {
            "name": "lden"
          },
          {
            "name": "ln"
          },
          {
            "name": "lden_categorical"
          },
          {
            "name": "ln_categorical"
          },
          {
            "name": "distance (noise)"
          },
          {
            "name": "Traffic"
          },
          {
            "name": "distance_traffic"
          },
          {
            "name": "traffic_load_all_roads"
          },
          {
            "name": "traffic_load_major_roads"
          },
          {
            "name": "traffic_density"
          },
          {
            "name": "Unhealthy food environment"
          },
          {
            "name": "unhealthy_facilities_density"
          },
          {
            "name": "unhealthy_facilities_density_osm"
          }
        ],
        "label": "label for test dataset for cohort 2",
        "name": "test dataset for testCohort2",
        "numberOfRows": 83737,
        "resource": {
          "id": "testCohort2",
          "name": "Name for test cohort 2"
        },
        "sinceVersion": "1959",
        "unitOfObservation": {
          "name": "medicine dispensation"
        },
        "untilVersion": "1985"
      },
      {
        "name": "test dataset for testCohort3",
        "resource": {
          "id": "testCohort3",
          "name": "testCohort3C"
        }
      },
      {
        "name": "test dataset for testCohort4",
        "resource": {
          "id": "testCohort4",
          "name": "testCohort4"
        }
      },
      {
        "description": "Table containing data concerning ultrasound",
        "label": "ultrasound_data",
        "name": "Ultrasound_all_SLC_20220428_893",
        "numberOfRows": 458,
        "resource": {
          "id": "Sepages",
          "name": "Suivi de l'Exposition \u00e0 la Pollution Atmosph\u00e9rique et Effet sur la"
        },
        "sinceVersion": "1.0.0",
        "unitOfObservation": {
          "name": "person"
        }
      },
      {
        "description": "Urban exposome dataset generated by Montserrat de Castro (ISGlobal)",
        "label": "Urban exposome dataset generated by Montserrat de Castro (ISGlobal)",
        "name": "Urban_ISGlobal",
        "resource": {
          "id": "PELAGIE",
          "name": "Perturbateurs Endocriniens: \u00c9tude Longitudinale sur les Anomalies de la Grossesse, l\u2019Infertilit"
        },
        "unitOfObservation": {
          "name": "Patient"
        }
      }
    ]
  }
}